{"strategy":{"MeanReversion_v1":{"trades":[{"pair":"BNB/USDT","stake_amount":32.4108,"max_stake_amount":32.4108,"amount":0.045,"open_date":"2026-05-31 07:35:00+00:00","close_date":"2026-05-31 08:10:00+00:00","open_rate":720.24,"close_rate":723.13,"fee_open":0.001,"fee_close":0.001,"trade_duration":35,"profit_ratio":0.002006532288105097,"profit_abs":0.06509835,"exit_reason":"roi","initial_stop_loss_abs":655.42,"initial_stop_loss_ratio":-0.09,"stop_loss_abs":655.42,"stop_loss_ratio":-0.09,"min_rate":718.76,"max_rate":723.76,"is_open":false,"enter_tag":"","leverage":1.0,"is_short":false,"open_timestamp":1780212900000,"close_timestamp":1780215000000,"orders":[{"amount":0.045,"safe_price":720.24,"ft_order_side":"buy","order_filled_timestamp":1780212900000,"ft_is_entry":true,"ft_order_tag":"","cost":32.443210799999996},{"amount":0.045,"safe_price":723.13,"ft_order_side":"sell","order_filled_timestamp":1780215000000,"ft_is_entry":false,"ft_order_tag":"roi","cost":32.573390849999996}],"funding_fees":0.0,"weekday":6},{"pair":"BNB/USDT","stake_amount":32.35916,"max_stake_amount":32.35916,"amount":0.046,"open_date":"2026-05-31 16:35:00+00:00","close_date":"2026-05-31 16:35:00+00:00","open_rate":703.46,"close_rate":709.1,"fee_open":0.001,"fee_close":0.001,"trade_duration":0,"profit_ratio":0.006003492427738298,"profit_abs":0.19446224,"exit_reason":"roi","initial_stop_loss_abs":640.15,"initial_stop_loss_ratio":-0.09,"stop_loss_abs":640.15,"stop_loss_ratio":-0.09,"min_rate":703.05,"max_rate":709.13,"is_open":false,"enter_tag":"","leverage":1.0,"is_short":false,"open_timestamp":1780245300000,"close_timestamp":1780245300000,"orders":[{"amount":0.046,"safe_price":703.46,"ft_order_side":"buy","order_filled_timestamp":1780245300000,"ft_is_entry":true,"ft_order_tag":"","cost":32.39151916},{"amount":0.046,"safe_price":709.1,"ft_order_side":"sell","order_filled_timestamp":1780245300000,"ft_is_entry":false,"ft_order_tag":"roi","cost":32.6512186}],"funding_fees":0.0,"weekday":6},{"pair":"BTC/USDT","stake_amount":32.64306,"max_stake_amount":32.64306,"amount":0.00051,"open_date":"2026-06-14 14:35:00+00:00","close_date":"2026-06-14 21:15:00+00:00","open_rate":64006.0,"close_rate":64262.41,"fee_open":0.001,"fee_close":0.001,"trade_duration":400,"profit_ratio":0.0020000246017659825,"profit_abs":0.06535221,"exit_reason":"roi","initial_stop_loss_abs":58245.46,"initial_stop_loss_ratio":-0.09,"stop_loss_abs":58245.46,"stop_loss_ratio":-0.09,"min_rate":63678.83,"max_rate":64949.0,"is_open":false,"enter_tag":"","leverage":1.0,"is_short":false,"open_timestamp":1781447700000,"close_timestamp":1781471700000,"orders":[{"amount":0.00051,"safe_price":64006.0,"ft_order_side":"buy","order_filled_timestamp":1781447700000,"ft_is_entry":true,"ft_order_tag":"","cost":32.675703060000004},{"amount":0.00051,"safe_price":64262.41,"ft_order_side":"sell","order_filled_timestamp":1781471700000,"ft_is_entry":false,"ft_order_tag":"roi","cost":32.8066029291}],"funding_fees":0.0,"weekday":6},{"pair":"BNB/USDT","stake_amount":32.79798,"max_stake_amount":32.79798,"amount":0.054,"open_date":"2026-06-14 14:40:00+00:00","close_date":"2026-06-14 21:15:00+00:00","open_rate":607.37,"close_rate":609.8,"fee_open":0.001,"fee_close":0.001,"trade_duration":395,"profit_ratio":0.0019948604337033135,"profit_abs":0.06549282,"exit_reason":"roi","initial_stop_loss_abs":552.71,"initial_stop_loss_ratio":-0.09,"stop_loss_abs":552.71,"stop_loss_ratio":-0.09,"min_rate":602.79,"max_rate":610.19,"is_open":false,"enter_tag":"","leverage":1.0,"is_short":false,"open_timestamp":1781448000000,"close_timestamp":1781471700000,"orders":[{"amount":0.054,"safe_price":607.37,"ft_order_side":"buy","order_filled_timestamp":1781448000000,"ft_is_entry":true,"ft_order_tag":"","cost":32.83077798},{"amount":0.054,"safe_price":609.8,"ft_order_side":"sell","order_filled_timestamp":1781471700000,"ft_is_entry":false,"ft_order_tag":"roi","cost":32.96212919999999}],"funding_fees":0.0,"weekday":6},{"pair":"LINK/USDT","stake_amount":33.11336,"max_stake_amount":33.11336,"amount":4.06,"open_date":"2026-06-16 02:30:00+00:00","close_date":"2026-06-16 03:00:00+00:00","open_rate":8.156,"close_rate":8.189,"fee_open":0.001,"fee_close":0.001,"trade_duration":30,"profit_ratio":0.002040014913972736,"profit_abs":0.0676193,"exit_reason":"roi","initial_stop_loss_abs":7.422,"initial_stop_loss_ratio":-0.09,"stop_loss_abs":7.422,"stop_loss_ratio":-0.09,"min_rate":8.152,"max_rate":8.201,"is_open":false,"enter_tag":"","leverage":1.0,"is_short":false,"open_timestamp":1781577000000,"close_timestamp":1781578800000,"orders":[{"amount":4.06,"safe_price":8.156,"ft_order_side":"buy","order_filled_timestamp":1781577000000,"ft_is_entry":true,"ft_order_tag":"","cost":33.146473359999995},{"amount":4.06,"safe_price":8.189,"ft_order_side":"sell","order_filled_timestamp":1781578800000,"ft_is_entry":false,"ft_order_tag":"roi","cost":33.28058733999999}],"funding_fees":0.0,"weekday":1},{"pair":"BNB/USDT","stake_amount":33.01128,"max_stake_amount":33.01128,"amount":0.054,"open_date":"2026-06-16 02:30:00+00:00","close_date":"2026-06-16 03:25:00+00:00","open_rate":611.32,"close_rate":613.77,"fee_open":0.001,"fee_close":0.001,"trade_duration":55,"profit_ratio":0.002001711564624605,"profit_abs":0.06614514,"exit_reason":"roi","initial_stop_loss_abs":556.31,"initial_stop_loss_ratio":-0.09,"stop_loss_abs":556.31,"stop_loss_ratio":-0.09,"min_rate":611.1,"max_rate":614.2,"is_open":false,"enter_tag":"","leverage":1.0,"is_short":false,"open_timestamp":1781577000000,"close_timestamp":1781580300000,"orders":[{"amount":0.054,"safe_price":611.32,"ft_order_side":"buy","order_filled_timestamp":1781577000000,"ft_is_entry":true,"ft_order_tag":"","cost":33.044291279999996},{"amount":0.054,"safe_price":613.77,"ft_order_side":"sell","order_filled_timestamp":1781580300000,"ft_is_entry":false,"ft_order_tag":"roi","cost":33.176723579999994}],"funding_fees":0.0,"weekday":1},{"pair":"BTC/USDT","stake_amount":32.888005,"max_stake_amount":32.888005,"amount":0.0005,"open_date":"2026-06-16 02:30:00+00:00","close_date":"2026-06-16 03:30:00+00:00","open_rate":65776.01,"close_rate":66039.51,"fee_open":0.001,"fee_close":0.001,"trade_duration":60,"profit_ratio":0.002000013790330655,"profit_abs":0.06584224,"exit_reason":"roi","initial_stop_loss_abs":59856.17,"initial_stop_loss_ratio":-0.09,"stop_loss_abs":59856.17,"stop_loss_ratio":-0.09,"min_rate":65650.0,"max_rate":66052.6,"is_open":false,"enter_tag":"","leverage":1.0,"is_short":false,"open_timestamp":1781577000000,"close_timestamp":1781580600000,"orders":[{"amount":0.0005,"safe_price":65776.01,"ft_order_side":"buy","order_filled_timestamp":1781577000000,"ft_is_entry":true,"ft_order_tag":"","cost":32.920893004999996},{"amount":0.0005,"safe_price":66039.51,"ft_order_side":"sell","order_filled_timestamp":1781580600000,"ft_is_entry":false,"ft_order_tag":"roi","cost":33.052774754999994}],"funding_fees":0.0,"weekday":1},{"pair":"LINK/USDT","stake_amount":33.18238,"max_stake_amount":33.18238,"amount":4.06,"open_date":"2026-06-17 08:45:00+00:00","close_date":"2026-06-17 09:25:00+00:00","open_rate":8.173,"close_rate":8.206,"fee_open":0.001,"fee_close":0.001,"trade_duration":40,"profit_ratio":0.002031615759744966,"profit_abs":0.06748126,"exit_reason":"roi","initial_stop_loss_abs":7.438,"initial_stop_loss_ratio":-0.09,"stop_loss_abs":7.438,"stop_loss_ratio":-0.09,"min_rate":8.15,"max_rate":8.213,"is_open":false,"enter_tag":"","leverage":1.0,"is_short":false,"open_timestamp":1781685900000,"close_timestamp":1781688300000,"orders":[{"amount":4.06,"safe_price":8.173,"ft_order_side":"buy","order_filled_timestamp":1781685900000,"ft_is_entry":true,"ft_order_tag":"","cost":33.215562379999994},{"amount":4.06,"safe_price":8.206,"ft_order_side":"sell","order_filled_timestamp":1781688300000,"ft_is_entry":false,"ft_order_tag":"roi","cost":33.34967635999999}],"funding_fees":0.0,"weekday":2}],"locks":[],"best_pair":{"key":"BNB/USDT","trades":4,"profit_mean":0.003001649178542829,"profit_mean_pct":0.3,"profit_total_abs":0.39119855,"profit_total":0.0039119854999999995,"profit_total_pct":0.39,"duration_avg":"2:01:00","wins":4,"draws":0,"losses":0,"winrate":1.0,"cagr":0.0486493141198574,"expectancy":0.0977996375,"expectancy_ratio":100.0,"sortino":-100.0,"sharpe":4.463903679278621,"calmar":-100.0,"sqn":3.0352,"profit_factor":0.0,"max_drawdown_account":0.0,"max_drawdown_abs":0.0},"worst_pair":{"key":"BTC/USDT","trades":2,"profit_mean":0.0020000191960483187,"profit_mean_pct":0.2,"profit_total_abs":0.13119445,"profit_total":0.0013119445,"profit_total_pct":0.13,"duration_avg":"3:50:00","wins":2,"draws":0,"losses":0,"winrate":1.0,"cagr":0.016079434783539792,"expectancy":0.065597225,"expectancy_ratio":100.0,"sortino":-100.0,"sharpe":340.99496600872953,"calmar":-100.0,"sqn":267.7274,"profit_factor":0.0,"max_drawdown_account":0.0,"max_drawdown_abs":0.0},"results_per_pair":[{"key":"BNB/USDT","trades":4,"profit_mean":0.003001649178542829,"profit_mean_pct":0.3,"profit_total_abs":0.39119855,"profit_total":0.0039119854999999995,"profit_total_pct":0.39,"duration_avg":"2:01:00","wins":4,"draws":0,"losses":0,"winrate":1.0,"cagr":0.0486493141198574,"expectancy":0.0977996375,"expectancy_ratio":100.0,"sortino":-100.0,"sharpe":4.463903679278621,"calmar":-100.0,"sqn":3.0352,"profit_factor":0.0,"max_drawdown_account":0.0,"max_drawdown_abs":0.0},{"key":"LINK/USDT","trades":2,"profit_mean":0.002035815336858851,"profit_mean_pct":0.2,"profit_total_abs":0.13510055999999998,"profit_total":0.0013510055999999997,"profit_total_pct":0.14,"duration_avg":"0:35:00","wins":2,"draws":0,"losses":0,"winrate":1.0,"cagr":0.016561792174602408,"expectancy":0.06755027999999999,"expectancy_ratio":100.0,"sortino":-100.0,"sharpe":1246.5433085413779,"calmar":-100.0,"sqn":978.7059,"profit_factor":0.0,"max_drawdown_account":0.0,"max_drawdown_abs":0.0},{"key":"BTC/USDT","trades":2,"profit_mean":0.0020000191960483187,"profit_mean_pct":0.2,"profit_total_abs":0.13119445,"profit_total":0.0013119445,"profit_total_pct":0.13,"duration_avg":"3:50:00","wins":2,"draws":0,"losses":0,"winrate":1.0,"cagr":0.016079434783539792,"expectancy":0.065597225,"expectancy_ratio":100.0,"sortino":-100.0,"sharpe":340.99496600872953,"calmar":-100.0,"sqn":267.7274,"profit_factor":0.0,"max_drawdown_account":0.0,"max_drawdown_abs":0.0},{"key":"TOTAL","trades":8,"profit_mean":0.0025097832224982067,"profit_mean_pct":0.25,"profit_total_abs":0.6574935599999999,"profit_total":0.006574935599999999,"profit_total_pct":0.66,"duration_avg":"2:07:00","wins":8,"draws":0,"losses":0,"winrate":1.0,"cagr":0.08299810225962467,"expectancy":0.08218669499999999,"expectancy_ratio":100.0,"sortino":-100.0,"sharpe":9.864773010749717,"calmar":-100.0,"sqn":5.123,"profit_factor":0.0,"max_drawdown_account":0.0,"max_drawdown_abs":0.0}],"results_per_enter_tag":[{"key":"","trades":8,"profit_mean":0.0025097832224982067,"profit_mean_pct":0.25,"profit_total_abs":0.6574935599999999,"profit_total":0.006574935599999999,"profit_total_pct":0.66,"duration_avg":"2:07:00","wins":8,"draws":0,"losses":0,"winrate":1.0,"cagr":0.08299810225962467,"expectancy":0.08218669499999999,"expectancy_ratio":100.0,"sortino":-100.0,"sharpe":9.864773010749717,"calmar":-100.0,"sqn":5.123,"profit_factor":0.0,"max_drawdown_account":0.0,"max_drawdown_abs":0.0},{"key":"TOTAL","trades":8,"profit_mean":0.0025097832224982067,"profit_mean_pct":0.25,"profit_total_abs":0.6574935599999999,"profit_total":0.006574935599999999,"profit_total_pct":0.66,"duration_avg":"2:07:00","wins":8,"draws":0,"losses":0,"winrate":1.0,"cagr":0.08299810225962467,"expectancy":0.08218669499999999,"expectancy_ratio":100.0,"sortino":-100.0,"sharpe":9.864773010749717,"calmar":-100.0,"sqn":5.123,"profit_factor":0.0,"max_drawdown_account":0.0,"max_drawdown_abs":0.0}],"exit_reason_summary":[{"key":"roi","trades":8,"profit_mean":0.0025097832224982067,"profit_mean_pct":0.25,"profit_total_abs":0.6574935599999999,"profit_total":0.006574935599999999,"profit_total_pct":0.66,"duration_avg":"2:07:00","wins":8,"draws":0,"losses":0,"winrate":1.0,"cagr":0.08299810225962467,"expectancy":0.08218669499999999,"expectancy_ratio":100.0,"sortino":-100.0,"sharpe":9.864773010749717,"calmar":-100.0,"sqn":5.123,"profit_factor":0.0,"max_drawdown_account":0.0,"max_drawdown_abs":0.0},{"key":"TOTAL","trades":8,"profit_mean":0.0025097832224982067,"profit_mean_pct":0.25,"profit_total_abs":0.6574935599999999,"profit_total":0.006574935599999999,"profit_total_pct":0.66,"duration_avg":"2:07:00","wins":8,"draws":0,"losses":0,"winrate":1.0,"cagr":0.08299810225962467,"expectancy":0.08218669499999999,"expectancy_ratio":100.0,"sortino":-100.0,"sharpe":9.864773010749717,"calmar":-100.0,"sqn":5.123,"profit_factor":0.0,"max_drawdown_account":0.0,"max_drawdown_abs":0.0}],"mix_tag_stats":[{"key":["","roi"],"trades":8,"profit_mean":0.0025097832224982067,"profit_mean_pct":0.25,"profit_total_abs":0.6574935599999999,"profit_total":0.006574935599999999,"profit_total_pct":0.66,"duration_avg":"2:07:00","wins":8,"draws":0,"losses":0,"winrate":1.0,"cagr":0.08299810225962467,"expectancy":0.08218669499999999,"expectancy_ratio":100.0,"sortino":-100.0,"sharpe":9.864773010749717,"calmar":-100.0,"sqn":5.123,"profit_factor":0.0,"max_drawdown_account":0.0,"max_drawdown_abs":0.0},{"key":"TOTAL","trades":8,"profit_mean":0.0025097832224982067,"profit_mean_pct":0.25,"profit_total_abs":0.6574935599999999,"profit_total":0.006574935599999999,"profit_total_pct":0.66,"duration_avg":"2:07:00","wins":8,"draws":0,"losses":0,"winrate":1.0,"cagr":0.08299810225962467,"expectancy":0.08218669499999999,"expectancy_ratio":100.0,"sortino":-100.0,"sharpe":9.864773010749717,"calmar":-100.0,"sqn":5.123,"profit_factor":0.0,"max_drawdown_account":0.0,"max_drawdown_abs":0.0}],"left_open_trades":[{"key":"TOTAL","trades":0,"profit_mean":0.0,"profit_mean_pct":0.0,"profit_total_abs":0.0,"profit_total":0.0,"profit_total_pct":0.0,"duration_avg":"0:00","wins":0,"draws":0,"losses":0,"winrate":0.0,"cagr":0.0,"expectancy":0.0,"expectancy_ratio":100.0,"sortino":0,"sharpe":0,"calmar":0.0,"sqn":0.0,"profit_factor":0.0,"max_drawdown_account":0.0,"max_drawdown_abs":0.0}],"total_trades":8,"trade_count_long":8,"trade_count_short":0,"total_volume":526.5215346391,"avg_stake_amount":32.800753125,"profit_mean":0.0025097832224982067,"profit_median":0.0020041219263648513,"profit_total":0.006574935599999999,"profit_total_long":0.006574935599999999,"profit_total_short":0.0,"profit_total_abs":0.6574935599999999,"profit_total_long_abs":0.6574935599999999,"profit_total_short_abs":0.0,"cagr":0.08299810225962467,"expectancy":0.08218669499999999,"expectancy_ratio":100.0,"sortino":-100.0,"sharpe":9.864773010749717,"calmar":-100.0,"sqn":5.123,"wallet_stats":{"start_balance":100.0,"end_balance":100.65749356,"high_balance":100.72057062,"low_balance":99.90821619,"sharpe":6.774031123462221,"sortino":-100.0,"calmar":92.67378874858842,"low_date":"2026-06-14 19:50:00","low_ts":1781466600000,"high_date":"2026-06-16 02:50:00","high_ts":1781578200000,"max_drawdown_account":0.00467393877542692,"max_relative_drawdown":0.00467393877542692,"max_drawdown_abs":0.4691576999999967,"drawdown_start":"2026-06-14 16:35:00","drawdown_start_ts":1781454900000,"drawdown_end":"2026-06-14 19:50:00","drawdown_end_ts":1781466600000,"drawdown_duration":"0 days 03:15:00","drawdown_duration_s":11700.0,"max_drawdown_low":-0.09178380999999547,"max_drawdown_high":0.3773738900000012},"profit_factor":0.0,"backtest_start":"2026-05-19 00:00:00","backtest_start_ts":1779148800000,"backtest_end":"2026-06-18 00:00:00","backtest_end_ts":1781740800000,"backtest_days":30,"backtest_run_start_ts":1781797280,"backtest_run_end_ts":1781797280,"trades_per_day":0.27,"market_change":-0.12698313972078015,"pairlist":["BTC/USDT","BNB/USDT","LINK/USDT"],"stake_amount":"unlimited","stake_currency":"USDT","stake_currency_decimals":3,"starting_balance":100.0,"dry_run_wallet":100.0,"final_balance":100.65749356,"rejected_signals":0,"timedout_entry_orders":0,"timedout_exit_orders":0,"canceled_trade_entries":0,"canceled_entry_orders":0,"replaced_entry_orders":0,"max_open_trades":3,"max_open_trades_setting":3,"timeframe":"5m","timeframe_detail":"","timerange":"20260519-20260618","enable_protections":false,"strategy_name":"MeanReversion_v1","freqaimodel":null,"freqai_identifier":null,"stoploss":-0.09,"trailing_stop":false,"trailing_stop_positive":null,"trailing_stop_positive_offset":0.0,"trailing_only_offset_is_reached":false,"use_custom_stoploss":false,"minimal_roi":{"0":0.006,"23":0.002,"72":0.002,"190":0.002},"use_exit_signal":true,"exit_profit_only":false,"exit_profit_offset":0.0,"ignore_roi_if_entry_signal":false,"trading_mode":"spot","margin_mode":"isolated","periodic_breakdown":{"day":[{"date":"31/05/2026","date_ts":1780185600000,"profit_abs":0.25956059,"wins":2,"draws":0,"losses":0,"trades":2,"profit_factor":0.0},{"date":"01/06/2026","date_ts":1780272000000,"profit_abs":0.0,"wins":0,"draws":0,"losses":0,"trades":0,"profit_factor":0.0},{"date":"02/06/2026","date_ts":1780358400000,"profit_abs":0.0,"wins":0,"draws":0,"losses":0,"trades":0,"profit_factor":0.0},{"date":"03/06/2026","date_ts":1780444800000,"profit_abs":0.0,"wins":0,"draws":0,"losses":0,"trades":0,"profit_factor":0.0},{"date":"04/06/2026","date_ts":1780531200000,"profit_abs":0.0,"wins":0,"draws":0,"losses":0,"trades":0,"profit_factor":0.0},{"date":"05/06/2026","date_ts":1780617600000,"profit_abs":0.0,"wins":0,"draws":0,"losses":0,"trades":0,"profit_factor":0.0},{"date":"06/06/2026","date_ts":1780704000000,"profit_abs":0.0,"wins":0,"draws":0,"losses":0,"trades":0,"profit_factor":0.0},{"date":"07/06/2026","date_ts":1780790400000,"profit_abs":0.0,"wins":0,"draws":0,"losses":0,"trades":0,"profit_factor":0.0},{"date":"08/06/2026","date_ts":1780876800000,"profit_abs":0.0,"wins":0,"draws":0,"losses":0,"trades":0,"profit_factor":0.0},{"date":"09/06/2026","date_ts":1780963200000,"profit_abs":0.0,"wins":0,"draws":0,"losses":0,"trades":0,"profit_factor":0.0},{"date":"10/06/2026","date_ts":1781049600000,"profit_abs":0.0,"wins":0,"draws":0,"losses":0,"trades":0,"profit_factor":0.0},{"date":"11/06/2026","date_ts":1781136000000,"profit_abs":0.0,"wins":0,"draws":0,"losses":0,"trades":0,"profit_factor":0.0},{"date":"12/06/2026","date_ts":1781222400000,"profit_abs":0.0,"wins":0,"draws":0,"losses":0,"trades":0,"profit_factor":0.0},{"date":"13/06/2026","date_ts":1781308800000,"profit_abs":0.0,"wins":0,"draws":0,"losses":0,"trades":0,"profit_factor":0.0},{"date":"14/06/2026","date_ts":1781395200000,"profit_abs":0.13084503,"wins":2,"draws":0,"losses":0,"trades":2,"profit_factor":0.0},{"date":"15/06/2026","date_ts":1781481600000,"profit_abs":0.0,"wins":0,"draws":0,"losses":0,"trades":0,"profit_factor":0.0},{"date":"16/06/2026","date_ts":1781568000000,"profit_abs":0.19960668,"wins":3,"draws":0,"losses":0,"trades":3,"profit_factor":0.0},{"date":"17/06/2026","date_ts":1781654400000,"profit_abs":0.06748126,"wins":1,"draws":0,"losses":0,"trades":1,"profit_factor":0.0}],"week":[{"date":"01/06/2026","date_ts":1780272000000,"profit_abs":0.25956059,"wins":2,"draws":0,"losses":0,"trades":2,"profit_factor":0.0},{"date":"08/06/2026","date_ts":1780876800000,"profit_abs":0.0,"wins":0,"draws":0,"losses":0,"trades":0,"profit_factor":0.0},{"date":"15/06/2026","date_ts":1781481600000,"profit_abs":0.13084503,"wins":2,"draws":0,"losses":0,"trades":2,"profit_factor":0.0},{"date":"22/06/2026","date_ts":1782086400000,"profit_abs":0.26708794,"wins":4,"draws":0,"losses":0,"trades":4,"profit_factor":0.0}],"month":[{"date":"31/05/2026","date_ts":1780185600000,"profit_abs":0.25956059,"wins":2,"draws":0,"losses":0,"trades":2,"profit_factor":0.0},{"date":"30/06/2026","date_ts":1782777600000,"profit_abs":0.39793297,"wins":6,"draws":0,"losses":0,"trades":6,"profit_factor":0.0}],"year":[{"date":"31/12/2026","date_ts":1798675200000,"profit_abs":0.65749356,"wins":8,"draws":0,"losses":0,"trades":8,"profit_factor":0.0}],"weekday":[{"date":"Tuesday","date_ts":1,"profit_abs":0.19960668,"wins":3,"draws":0,"losses":0,"trades":3,"profit_factor":0.0},{"date":"Wednesday","date_ts":2,"profit_abs":0.06748126,"wins":1,"draws":0,"losses":0,"trades":1,"profit_factor":0.0},{"date":"Sunday","date_ts":6,"profit_abs":0.39040562,"wins":4,"draws":0,"losses":0,"trades":4,"profit_factor":0.0}]},"backtest_best_day":0.008010024715843396,"backtest_worst_day":0.0,"backtest_best_day_abs":0.25956059,"backtest_worst_day_abs":0.0,"winning_days":4,"draw_days":14,"losing_days":0,"daily_profit":[["2026-05-31",0.25956059],["2026-06-01",0.0],["2026-06-02",0.0],["2026-06-03",0.0],["2026-06-04",0.0],["2026-06-05",0.0],["2026-06-06",0.0],["2026-06-07",0.0],["2026-06-08",0.0],["2026-06-09",0.0],["2026-06-10",0.0],["2026-06-11",0.0],["2026-06-12",0.0],["2026-06-13",0.0],["2026-06-14",0.13084503],["2026-06-15",0.0],["2026-06-16",0.19960668],["2026-06-17",0.06748126]],"wins":8,"losses":0,"draws":0,"winrate":1.0,"holding_avg":"2:07:00","holding_avg_s":7620.0,"winner_holding_min":"0d 00:00","winner_holding_min_s":0.0,"winner_holding_max":"0d 06:40","winner_holding_max_s":24000.0,"winner_holding_avg":"0d 02:07","winner_holding_avg_s":7620.0,"loser_holding_min":"0d 00:00","loser_holding_min_s":0.0,"loser_holding_max":"0d 00:00","loser_holding_max_s":0.0,"loser_holding_avg":"0d 00:00","loser_holding_avg_s":0.0,"max_consecutive_wins":8,"max_consecutive_losses":0,"max_drawdown_account":0.0,"max_relative_drawdown":0.0,"max_drawdown_abs":0.0,"drawdown_start":"2026-05-31 08:10:00","drawdown_start_ts":1780215000000.0,"drawdown_end":"2026-05-31 08:10:00","drawdown_end_ts":1780215000000.0,"drawdown_duration":"0 days 00:00:00","drawdown_duration_s":0.0,"max_drawdown_low":0.0,"max_drawdown_high":0.0,"csum_min":100.06509835,"csum_max":100.65749356}},"strategy_comparison":[{"key":"MeanReversion_v1","trades":8,"profit_mean":0.0025097832224982067,"profit_mean_pct":0.25,"profit_total_abs":0.6574935599999999,"profit_total":0.006574935599999999,"profit_total_pct":0.66,"duration_avg":"2:07:00","wins":8,"draws":0,"losses":0,"winrate":1.0,"cagr":0.08299810225962467,"expectancy":0.08218669499999999,"expectancy_ratio":100.0,"sortino":-100.0,"sharpe":9.864773010749717,"calmar":-100.0,"sqn":5.123,"profit_factor":0.0,"max_drawdown_account":0.0,"max_drawdown_abs":"0"}]}