[
  {
    "pair": "ARB/USDT",
    "net_profit_currency": 2.0122077400000005,
    "net_profit_pct": 2.0122077400000005,
    "total_trades": 40,
    "win_count": 23,
    "loss_count": 17,
    "win_rate_pct": 57.49999999999999,
    "avg_trade_result_pct": 0.2317750672333275,
    "avg_trade_duration_minutes": 92.0,
    "pair_classification": null,
    "classification_rationale": null
  },
  {
    "pair": "STRK/USDT",
    "net_profit_currency": 1.91422713,
    "net_profit_pct": 1.91422713,
    "total_trades": 69,
    "win_count": 40,
    "loss_count": 29,
    "win_rate_pct": 57.971014492753625,
    "avg_trade_result_pct": 0.0713182227171888,
    "avg_trade_duration_minutes": 76.0,
    "pair_classification": null,
    "classification_rationale": null
  },
  {
    "pair": "ADA/USDT",
    "net_profit_currency": 1.36930737,
    "net_profit_pct": 1.36930737,
    "total_trades": 66,
    "win_count": 33,
    "loss_count": 33,
    "win_rate_pct": 50.0,
    "avg_trade_result_pct": -0.009702442029709985,
    "avg_trade_duration_minutes": 115.0,
    "pair_classification": null,
    "classification_rationale": null
  },
  {
    "pair": "DOT/USDT",
    "net_profit_currency": 0.82909433,
    "net_profit_pct": 0.8290943299999999,
    "total_trades": 18,
    "win_count": 11,
    "loss_count": 7,
    "win_rate_pct": 61.111111111111114,
    "avg_trade_result_pct": 0.200303457973735,
    "avg_trade_duration_minutes": 118.0,
    "pair_classification": null,
    "classification_rationale": null
  },
  {
    "pair": "NEAR/USDT",
    "net_profit_currency": 0.28758799999999995,
    "net_profit_pct": 0.28758799999999995,
    "total_trades": 44,
    "win_count": 21,
    "loss_count": 23,
    "win_rate_pct": 47.72727272727273,
    "avg_trade_result_pct": -0.013877612716572103,
    "avg_trade_duration_minutes": 105.0,
    "pair_classification": null,
    "classification_rationale": null
  },
  {
    "pair": "AXS/USDT",
    "net_profit_currency": 0.20547506000000001,
    "net_profit_pct": 0.20547506000000004,
    "total_trades": 26,
    "win_count": 14,
    "loss_count": 12,
    "win_rate_pct": 53.84615384615385,
    "avg_trade_result_pct": -0.118534453563013,
    "avg_trade_duration_minutes": 109.0,
    "pair_classification": null,
    "classification_rationale": null
  },
  {
    "pair": "PENDLE/USDT",
    "net_profit_currency": 0.1049503,
    "net_profit_pct": 0.1049503,
    "total_trades": 95,
    "win_count": 49,
    "loss_count": 46,
    "win_rate_pct": 51.578947368421055,
    "avg_trade_result_pct": 0.015681040124766597,
    "avg_trade_duration_minutes": 112.0,
    "pair_classification": null,
    "classification_rationale": null
  },
  {
    "pair": "XLM/USDT",
    "net_profit_currency": 0.0,
    "net_profit_pct": 0.0,
    "total_trades": 0,
    "win_count": 0,
    "loss_count": 0,
    "win_rate_pct": 0.0,
    "avg_trade_result_pct": 0.0,
    "avg_trade_duration_minutes": null,
    "pair_classification": null,
    "classification_rationale": null
  },
  {
    "pair": "SAND/USDT",
    "net_profit_currency": 0.0,
    "net_profit_pct": 0.0,
    "total_trades": 0,
    "win_count": 0,
    "loss_count": 0,
    "win_rate_pct": 0.0,
    "avg_trade_result_pct": 0.0,
    "avg_trade_duration_minutes": null,
    "pair_classification": null,
    "classification_rationale": null
  },
  {
    "pair": "APT/USDT",
    "net_profit_currency": 0.0,
    "net_profit_pct": 0.0,
    "total_trades": 0,
    "win_count": 0,
    "loss_count": 0,
    "win_rate_pct": 0.0,
    "avg_trade_result_pct": 0.0,
    "avg_trade_duration_minutes": null,
    "pair_classification": null,
    "classification_rationale": null
  },
  {
    "pair": "EGLD/USDT",
    "net_profit_currency": 0.0,
    "net_profit_pct": 0.0,
    "total_trades": 0,
    "win_count": 0,
    "loss_count": 0,
    "win_rate_pct": 0.0,
    "avg_trade_result_pct": 0.0,
    "avg_trade_duration_minutes": null,
    "pair_classification": null,
    "classification_rationale": null
  },
  {
    "pair": "GALA/USDT",
    "net_profit_currency": 0.0,
    "net_profit_pct": 0.0,
    "total_trades": 0,
    "win_count": 0,
    "loss_count": 0,
    "win_rate_pct": 0.0,
    "avg_trade_result_pct": 0.0,
    "avg_trade_duration_minutes": null,
    "pair_classification": null,
    "classification_rationale": null
  },
  {
    "pair": "HBAR/USDT",
    "net_profit_currency": 0.0,
    "net_profit_pct": 0.0,
    "total_trades": 0,
    "win_count": 0,
    "loss_count": 0,
    "win_rate_pct": 0.0,
    "avg_trade_result_pct": 0.0,
    "avg_trade_duration_minutes": null,
    "pair_classification": null,
    "classification_rationale": null
  },
  {
    "pair": "SEI/USDT",
    "net_profit_currency": 0.0,
    "net_profit_pct": 0.0,
    "total_trades": 0,
    "win_count": 0,
    "loss_count": 0,
    "win_rate_pct": 0.0,
    "avg_trade_result_pct": 0.0,
    "avg_trade_duration_minutes": null,
    "pair_classification": null,
    "classification_rationale": null
  },
  {
    "pair": "COMP/USDT",
    "net_profit_currency": 0.0,
    "net_profit_pct": 0.0,
    "total_trades": 0,
    "win_count": 0,
    "loss_count": 0,
    "win_rate_pct": 0.0,
    "avg_trade_result_pct": 0.0,
    "avg_trade_duration_minutes": null,
    "pair_classification": null,
    "classification_rationale": null
  },
  {
    "pair": "ENJ/USDT",
    "net_profit_currency": -0.3083500300000001,
    "net_profit_pct": -0.3083500300000001,
    "total_trades": 17,
    "win_count": 7,
    "loss_count": 10,
    "win_rate_pct": 41.17647058823529,
    "avg_trade_result_pct": -0.29007865416501266,
    "avg_trade_duration_minutes": 87.0,
    "pair_classification": null,
    "classification_rationale": null
  },
  {
    "pair": "SOL/USDT",
    "net_profit_currency": -0.54146461,
    "net_profit_pct": -0.54146461,
    "total_trades": 39,
    "win_count": 17,
    "loss_count": 22,
    "win_rate_pct": 43.58974358974359,
    "avg_trade_result_pct": -0.11993675673100089,
    "avg_trade_duration_minutes": 121.0,
    "pair_classification": null,
    "classification_rationale": null
  },
  {
    "pair": "OP/USDT",
    "net_profit_currency": -0.6030708800000001,
    "net_profit_pct": -0.6030708800000001,
    "total_trades": 20,
    "win_count": 9,
    "loss_count": 11,
    "win_rate_pct": 45.0,
    "avg_trade_result_pct": -0.3561632536224544,
    "avg_trade_duration_minutes": 119.0,
    "pair_classification": null,
    "classification_rationale": null
  },
  {
    "pair": "MINA/USDT",
    "net_profit_currency": -0.6906394300000002,
    "net_profit_pct": -0.6906394300000002,
    "total_trades": 57,
    "win_count": 31,
    "loss_count": 26,
    "win_rate_pct": 54.385964912280706,
    "avg_trade_result_pct": -0.12000283754056487,
    "avg_trade_duration_minutes": 82.0,
    "pair_classification": null,
    "classification_rationale": null
  },
  {
    "pair": "SUI/USDT",
    "net_profit_currency": -0.75975634,
    "net_profit_pct": -0.75975634,
    "total_trades": 34,
    "win_count": 15,
    "loss_count": 19,
    "win_rate_pct": 44.11764705882353,
    "avg_trade_result_pct": -0.1167878303819747,
    "avg_trade_duration_minutes": 116.0,
    "pair_classification": null,
    "classification_rationale": null
  },
  {
    "pair": "ZK/USDT",
    "net_profit_currency": -0.7837812899999999,
    "net_profit_pct": -0.7837812899999997,
    "total_trades": 48,
    "win_count": 25,
    "loss_count": 23,
    "win_rate_pct": 52.083333333333336,
    "avg_trade_result_pct": -0.34035033745585985,
    "avg_trade_duration_minutes": 99.0,
    "pair_classification": null,
    "classification_rationale": null
  },
  {
    "pair": "TIA/USDT",
    "net_profit_currency": -0.88367226,
    "net_profit_pct": -0.88367226,
    "total_trades": 38,
    "win_count": 20,
    "loss_count": 18,
    "win_rate_pct": 52.63157894736842,
    "avg_trade_result_pct": -0.3347115519526538,
    "avg_trade_duration_minutes": 96.0,
    "pair_classification": null,
    "classification_rationale": null
  },
  {
    "pair": "STX/USDT",
    "net_profit_currency": -1.22850079,
    "net_profit_pct": -1.22850079,
    "total_trades": 23,
    "win_count": 13,
    "loss_count": 10,
    "win_rate_pct": 56.52173913043478,
    "avg_trade_result_pct": -0.02536891823542693,
    "avg_trade_duration_minutes": 112.0,
    "pair_classification": null,
    "classification_rationale": null
  },
  {
    "pair": "CRV/USDT",
    "net_profit_currency": -1.3529473500000009,
    "net_profit_pct": -1.3529473500000009,
    "total_trades": 80,
    "win_count": 39,
    "loss_count": 41,
    "win_rate_pct": 48.75,
    "avg_trade_result_pct": -0.1939071421951101,
    "avg_trade_duration_minutes": 103.0,
    "pair_classification": null,
    "classification_rationale": null
  },
  {
    "pair": "FIL/USDT",
    "net_profit_currency": -1.3791887699999996,
    "net_profit_pct": -1.3791887699999996,
    "total_trades": 63,
    "win_count": 25,
    "loss_count": 38,
    "win_rate_pct": 39.682539682539684,
    "avg_trade_result_pct": -0.22237385664160622,
    "avg_trade_duration_minutes": 92.0,
    "pair_classification": null,
    "classification_rationale": null
  },
  {
    "pair": "AAVE/USDT",
    "net_profit_currency": -1.4295089199999997,
    "net_profit_pct": -1.4295089199999997,
    "total_trades": 47,
    "win_count": 21,
    "loss_count": 26,
    "win_rate_pct": 44.680851063829785,
    "avg_trade_result_pct": -0.34314501291208094,
    "avg_trade_duration_minutes": 132.0,
    "pair_classification": null,
    "classification_rationale": null
  },
  {
    "pair": "MANA/USDT",
    "net_profit_currency": -1.5949229,
    "net_profit_pct": -1.5949228999999998,
    "total_trades": 27,
    "win_count": 10,
    "loss_count": 17,
    "win_rate_pct": 37.03703703703704,
    "avg_trade_result_pct": -0.41881705857364304,
    "avg_trade_duration_minutes": 110.0,
    "pair_classification": null,
    "classification_rationale": null
  },
  {
    "pair": "ETH/USDT",
    "net_profit_currency": -1.63962815,
    "net_profit_pct": -1.6396281500000003,
    "total_trades": 37,
    "win_count": 14,
    "loss_count": 23,
    "win_rate_pct": 37.83783783783784,
    "avg_trade_result_pct": -0.17543023205640448,
    "avg_trade_duration_minutes": 104.0,
    "pair_classification": null,
    "classification_rationale": null
  },
  {
    "pair": "ETC/USDT",
    "net_profit_currency": -1.7531075999999999,
    "net_profit_pct": -1.7531075999999999,
    "total_trades": 22,
    "win_count": 8,
    "loss_count": 14,
    "win_rate_pct": 36.36363636363637,
    "avg_trade_result_pct": -0.49959909354904514,
    "avg_trade_duration_minutes": 107.0,
    "pair_classification": null,
    "classification_rationale": null
  },
  {
    "pair": "BLUR/USDT",
    "net_profit_currency": -2.0542949799999994,
    "net_profit_pct": -2.0542949799999994,
    "total_trades": 38,
    "win_count": 16,
    "loss_count": 22,
    "win_rate_pct": 42.10526315789473,
    "avg_trade_result_pct": -0.19885939651692286,
    "avg_trade_duration_minutes": 106.0,
    "pair_classification": null,
    "classification_rationale": null
  },
  {
    "pair": "BTC/USDT",
    "net_profit_currency": -2.1135868300000005,
    "net_profit_pct": -2.1135868300000005,
    "total_trades": 68,
    "win_count": 18,
    "loss_count": 50,
    "win_rate_pct": 26.47058823529412,
    "avg_trade_result_pct": -0.2635663398191505,
    "avg_trade_duration_minutes": 125.0,
    "pair_classification": null,
    "classification_rationale": null
  },
  {
    "pair": "SUSHI/USDT",
    "net_profit_currency": -2.1631672899999996,
    "net_profit_pct": -2.1631672899999996,
    "total_trades": 17,
    "win_count": 7,
    "loss_count": 10,
    "win_rate_pct": 41.17647058823529,
    "avg_trade_result_pct": -0.7644510603624786,
    "avg_trade_duration_minutes": 105.0,
    "pair_classification": null,
    "classification_rationale": null
  },
  {
    "pair": "RPL/USDT",
    "net_profit_currency": -2.2025888999999994,
    "net_profit_pct": -2.2025888999999994,
    "total_trades": 68,
    "win_count": 34,
    "loss_count": 34,
    "win_rate_pct": 50.0,
    "avg_trade_result_pct": -0.2635159453319746,
    "avg_trade_duration_minutes": 107.0,
    "pair_classification": null,
    "classification_rationale": null
  },
  {
    "pair": "XRP/USDT",
    "net_profit_currency": -2.2359714100000003,
    "net_profit_pct": -2.2359714100000003,
    "total_trades": 209,
    "win_count": 98,
    "loss_count": 111,
    "win_rate_pct": 46.889952153110045,
    "avg_trade_result_pct": -0.0527817724455541,
    "avg_trade_duration_minutes": 120.0,
    "pair_classification": null,
    "classification_rationale": null
  },
  {
    "pair": "SNX/USDT",
    "net_profit_currency": -2.3713639999999994,
    "net_profit_pct": -2.3713639999999994,
    "total_trades": 88,
    "win_count": 50,
    "loss_count": 38,
    "win_rate_pct": 56.81818181818182,
    "avg_trade_result_pct": -0.16656343065716978,
    "avg_trade_duration_minutes": 88.0,
    "pair_classification": null,
    "classification_rationale": null
  },
  {
    "pair": "VET/USDT",
    "net_profit_currency": -2.5432674200000003,
    "net_profit_pct": -2.5432674200000003,
    "total_trades": 93,
    "win_count": 41,
    "loss_count": 52,
    "win_rate_pct": 44.086021505376344,
    "avg_trade_result_pct": -0.26733292064917114,
    "avg_trade_duration_minutes": 113.0,
    "pair_classification": null,
    "classification_rationale": null
  },
  {
    "pair": "ICP/USDT",
    "net_profit_currency": -2.6936488699999996,
    "net_profit_pct": -2.6936488699999996,
    "total_trades": 67,
    "win_count": 33,
    "loss_count": 34,
    "win_rate_pct": 49.25373134328358,
    "avg_trade_result_pct": -0.3703654618318527,
    "avg_trade_duration_minutes": 96.0,
    "pair_classification": null,
    "classification_rationale": null
  },
  {
    "pair": "BNB/USDT",
    "net_profit_currency": -3.40116122,
    "net_profit_pct": -3.40116122,
    "total_trades": 137,
    "win_count": 50,
    "loss_count": 87,
    "win_rate_pct": 36.496350364963504,
    "avg_trade_result_pct": -0.17439198994378916,
    "avg_trade_duration_minutes": 123.0,
    "pair_classification": null,
    "classification_rationale": null
  },
  {
    "pair": "AVAX/USDT",
    "net_profit_currency": -3.5479619,
    "net_profit_pct": -3.5479619,
    "total_trades": 48,
    "win_count": 18,
    "loss_count": 30,
    "win_rate_pct": 37.5,
    "avg_trade_result_pct": -0.4634558455671554,
    "avg_trade_duration_minutes": 117.0,
    "pair_classification": null,
    "classification_rationale": null
  },
  {
    "pair": "IMX/USDT",
    "net_profit_currency": -3.732320729999999,
    "net_profit_pct": -3.7323207299999996,
    "total_trades": 107,
    "win_count": 48,
    "loss_count": 59,
    "win_rate_pct": 44.85981308411215,
    "avg_trade_result_pct": -0.19710700507601236,
    "avg_trade_duration_minutes": 100.0,
    "pair_classification": null,
    "classification_rationale": null
  },
  {
    "pair": "GMX/USDT",
    "net_profit_currency": -3.8358429700000003,
    "net_profit_pct": -3.8358429700000003,
    "total_trades": 83,
    "win_count": 33,
    "loss_count": 50,
    "win_rate_pct": 39.75903614457831,
    "avg_trade_result_pct": -0.17451089826149488,
    "avg_trade_duration_minutes": 105.0,
    "pair_classification": null,
    "classification_rationale": null
  },
  {
    "pair": "DYDX/USDT",
    "net_profit_currency": -3.87113588,
    "net_profit_pct": -3.8711358800000006,
    "total_trades": 50,
    "win_count": 18,
    "loss_count": 32,
    "win_rate_pct": 36.0,
    "avg_trade_result_pct": -0.5186363849487032,
    "avg_trade_duration_minutes": 104.0,
    "pair_classification": null,
    "classification_rationale": null
  },
  {
    "pair": "DOGE/USDT",
    "net_profit_currency": -4.15600942,
    "net_profit_pct": -4.15600942,
    "total_trades": 390,
    "win_count": 167,
    "loss_count": 223,
    "win_rate_pct": 42.82051282051282,
    "avg_trade_result_pct": -0.2338433727911851,
    "avg_trade_duration_minutes": 125.0,
    "pair_classification": null,
    "classification_rationale": null
  },
  {
    "pair": "YFI/USDT",
    "net_profit_currency": -4.46401519,
    "net_profit_pct": -4.46401519,
    "total_trades": 156,
    "win_count": 65,
    "loss_count": 91,
    "win_rate_pct": 41.66666666666667,
    "avg_trade_result_pct": -0.18164356671941528,
    "avg_trade_duration_minutes": 126.0,
    "pair_classification": null,
    "classification_rationale": null
  },
  {
    "pair": "INJ/USDT",
    "net_profit_currency": -4.5345627,
    "net_profit_pct": -4.5345627,
    "total_trades": 35,
    "win_count": 10,
    "loss_count": 25,
    "win_rate_pct": 28.57142857142857,
    "avg_trade_result_pct": -0.863818523712483,
    "avg_trade_duration_minutes": 97.0,
    "pair_classification": null,
    "classification_rationale": null
  },
  {
    "pair": "BCH/USDT",
    "net_profit_currency": -5.1172124000000005,
    "net_profit_pct": -5.1172124000000005,
    "total_trades": 87,
    "win_count": 31,
    "loss_count": 56,
    "win_rate_pct": 35.63218390804598,
    "avg_trade_result_pct": -0.3192109552459226,
    "avg_trade_duration_minutes": 134.0,
    "pair_classification": null,
    "classification_rationale": null
  },
  {
    "pair": "ALGO/USDT",
    "net_profit_currency": -5.4158551,
    "net_profit_pct": -5.4158551,
    "total_trades": 121,
    "win_count": 63,
    "loss_count": 58,
    "win_rate_pct": 52.066115702479344,
    "avg_trade_result_pct": -0.13538414010049557,
    "avg_trade_duration_minutes": 110.0,
    "pair_classification": null,
    "classification_rationale": null
  },
  {
    "pair": "SHIB/USDT",
    "net_profit_currency": -5.5143172,
    "net_profit_pct": -5.5143172,
    "total_trades": 540,
    "win_count": 215,
    "loss_count": 325,
    "win_rate_pct": 39.81481481481482,
    "avg_trade_result_pct": -0.20951368615511826,
    "avg_trade_duration_minutes": 127.0,
    "pair_classification": null,
    "classification_rationale": null
  },
  {
    "pair": "LDO/USDT",
    "net_profit_currency": -5.583856099999999,
    "net_profit_pct": -5.583856099999999,
    "total_trades": 79,
    "win_count": 35,
    "loss_count": 44,
    "win_rate_pct": 44.303797468354425,
    "avg_trade_result_pct": -0.31357052218699627,
    "avg_trade_duration_minutes": 97.0,
    "pair_classification": null,
    "classification_rationale": null
  },
  {
    "pair": "TRX/USDT",
    "net_profit_currency": -5.85178393,
    "net_profit_pct": -5.85178393,
    "total_trades": 187,
    "win_count": 71,
    "loss_count": 116,
    "win_rate_pct": 37.967914438502675,
    "avg_trade_result_pct": -0.19973693471665976,
    "avg_trade_duration_minutes": 133.0,
    "pair_classification": null,
    "classification_rationale": null
  },
  {
    "pair": "XTZ/USDT",
    "net_profit_currency": -7.185949989999998,
    "net_profit_pct": -7.185949989999998,
    "total_trades": 211,
    "win_count": 95,
    "loss_count": 115,
    "win_rate_pct": 45.023696682464454,
    "avg_trade_result_pct": -0.22543235923515031,
    "avg_trade_duration_minutes": 119.0,
    "pair_classification": null,
    "classification_rationale": null
  }
]