{
  "session_id": "32f8a60e-ea94-448e-be88-fb11194ead38",
  "status": "completed",
  "total": 4,
  "completed": 4,
  "results": {
    "MATIC/USDT + LINK/USDT + ATOM/USDT + UNI/USDT": {
      "group": "MATIC/USDT + LINK/USDT + ATOM/USDT + UNI/USDT",
      "pairs": [
        "MATIC/USDT",
        "LINK/USDT",
        "ATOM/USDT",
        "UNI/USDT"
      ],
      "status": "completed",
      "total_profit_pct": -11.8836,
      "win_rate": 50.72,
      "sharpe_ratio": -8.0663,
      "max_drawdown": 13.5277,
      "total_trades": 138
    },
    "PYTH/USDT + JTO/USDT + WIF/USDT + BONK/USDT": {
      "group": "PYTH/USDT + JTO/USDT + WIF/USDT + BONK/USDT",
      "pairs": [
        "PYTH/USDT",
        "JTO/USDT",
        "WIF/USDT",
        "BONK/USDT"
      ],
      "status": "completed",
      "total_profit_pct": -17.8634,
      "win_rate": 42.86,
      "sharpe_ratio": -14.6965,
      "max_drawdown": 18.079,
      "total_trades": 168
    },
    "BTC/USDT + ETH/USDT + BNB/USDT + SOL/USDT": {
      "group": "BTC/USDT + ETH/USDT + BNB/USDT + SOL/USDT",
      "pairs": [
        "BTC/USDT",
        "ETH/USDT",
        "BNB/USDT",
        "SOL/USDT"
      ],
      "status": "completed",
      "total_profit_pct": -17.8634,
      "win_rate": 42.86,
      "sharpe_ratio": -14.6965,
      "max_drawdown": 18.079,
      "total_trades": 168
    },
    "LTC/USDT + BCH/USDT + ETC/USDT + DOGE/USDT": {
      "group": "LTC/USDT + BCH/USDT + ETC/USDT + DOGE/USDT",
      "pairs": [
        "LTC/USDT",
        "BCH/USDT",
        "ETC/USDT",
        "DOGE/USDT"
      ],
      "status": "completed",
      "total_profit_pct": -17.8634,
      "win_rate": 42.86,
      "sharpe_ratio": -14.6965,
      "max_drawdown": 18.079,
      "total_trades": 168
    }
  },
  "strategy_name": "AIStrategy",
  "timeframe": "5m",
  "timerange": "20260321-20260619",
  "dry_run_wallet": 100.0,
  "max_open_trades": 4,
  "pairs": [
    "MATIC/USDT",
    "LINK/USDT",
    "ATOM/USDT",
    "UNI/USDT",
    "PYTH/USDT",
    "JTO/USDT",
    "WIF/USDT",
    "BONK/USDT",
    "BTC/USDT",
    "ETH/USDT",
    "BNB/USDT",
    "SOL/USDT",
    "LTC/USDT",
    "BCH/USDT",
    "ETC/USDT",
    "DOGE/USDT"
  ],
  "created_at": "2026-06-19T11:56:58.819621+00:00",
  "completed_at": "2026-06-19T11:57:08.264319+00:00"
}