[
  {
    "pair": "BTC/USDT",
    "net_profit_currency": 0.18369345,
    "net_profit_pct": 0.18369345,
    "total_trades": 1,
    "win_count": 1,
    "loss_count": 0,
    "win_rate_pct": 100.0,
    "avg_trade_result_pct": 0.5851171480095299,
    "avg_trade_duration_minutes": 4885.0,
    "pair_classification": null,
    "classification_rationale": null
  },
  {
    "pair": "LINK/USDT",
    "net_profit_currency": -0.30827861,
    "net_profit_pct": -0.30827861,
    "total_trades": 1,
    "win_count": 0,
    "loss_count": 1,
    "win_rate_pct": 0.0,
    "avg_trade_result_pct": -0.9706943375408309,
    "avg_trade_duration_minutes": 2730.0,
    "pair_classification": null,
    "classification_rationale": null
  },
  {
    "pair": "BNB/USDT",
    "net_profit_currency": -3.9875047,
    "net_profit_pct": -3.9875047000000006,
    "total_trades": 2,
    "win_count": 0,
    "loss_count": 2,
    "win_rate_pct": 0.0,
    "avg_trade_result_pct": -6.159952766960399,
    "avg_trade_duration_minutes": 4472.0,
    "pair_classification": null,
    "classification_rationale": null
  }
]