{
  "equity_curve": [
    {
      "ts": 1780519500000,
      "equity": 95.40236575
    },
    {
      "ts": 1781740800000,
      "equity": 95.58605920000001
    },
    {
      "ts": 1781740800000,
      "equity": 95.23166020000001
    },
    {
      "ts": 1781740800000,
      "equity": 94.92575906
    }
  ],
  "drawdown_curve": [
    {
      "ts": 1780519500000,
      "drawdown_pct": -4.597634249999999
    },
    {
      "ts": 1781740800000,
      "drawdown_pct": -4.413940799999992
    },
    {
      "ts": 1781740800000,
      "drawdown_pct": -4.768339799999993
    },
    {
      "ts": 1781740800000,
      "drawdown_pct": -5.074240939999996
    }
  ],
  "profit_ratio_histogram": [
    {
      "left": -0.14171329337107408,
      "right": -0.1367944778760351,
      "count": 1
    },
    {
      "left": -0.1367944778760351,
      "right": -0.13187566238099613,
      "count": 0
    },
    {
      "left": -0.13187566238099613,
      "right": -0.12695684688595715,
      "count": 0
    },
    {
      "left": -0.12695684688595715,
      "right": -0.12203803139091818,
      "count": 0
    },
    {
      "left": -0.12203803139091816,
      "right": -0.11711921589587919,
      "count": 0
    },
    {
      "left": -0.11711921589587919,
      "right": -0.11220040040084021,
      "count": 0
    },
    {
      "left": -0.1122004004008402,
      "right": -0.10728158490580122,
      "count": 0
    },
    {
      "left": -0.10728158490580122,
      "right": -0.10236276941076225,
      "count": 0
    },
    {
      "left": -0.10236276941076225,
      "right": -0.09744395391572327,
      "count": 0
    },
    {
      "left": -0.09744395391572327,
      "right": -0.0925251384206843,
      "count": 0
    },
    {
      "left": -0.0925251384206843,
      "right": -0.08760632292564532,
      "count": 0
    },
    {
      "left": -0.08760632292564531,
      "right": -0.08268750743060634,
      "count": 0
    },
    {
      "left": -0.08268750743060634,
      "right": -0.07776869193556736,
      "count": 0
    },
    {
      "left": -0.07776869193556736,
      "right": -0.07284987644052839,
      "count": 0
    },
    {
      "left": -0.07284987644052837,
      "right": -0.0679310609454894,
      "count": 0
    },
    {
      "left": -0.0679310609454894,
      "right": -0.06301224545045042,
      "count": 0
    },
    {
      "left": -0.06301224545045042,
      "right": -0.058093429955411446,
      "count": 0
    },
    {
      "left": -0.058093429955411446,
      "right": -0.05317461446037247,
      "count": 0
    },
    {
      "left": -0.05317461446037247,
      "right": -0.048255798965333496,
      "count": 0
    },
    {
      "left": -0.04825579896533348,
      "right": -0.04333698347029451,
      "count": 0
    },
    {
      "left": -0.04333698347029451,
      "right": -0.03841816797525553,
      "count": 0
    },
    {
      "left": -0.03841816797525553,
      "right": -0.03349935248021656,
      "count": 0
    },
    {
      "left": -0.03349935248021654,
      "right": -0.028580536985177565,
      "count": 0
    },
    {
      "left": -0.028580536985177568,
      "right": -0.02366172149013859,
      "count": 0
    },
    {
      "left": -0.023661721490138593,
      "right": -0.018742905995099614,
      "count": 0
    },
    {
      "left": -0.018742905995099618,
      "right": -0.01382409050006064,
      "count": 0
    },
    {
      "left": -0.013824090500060643,
      "right": -0.008905275005021664,
      "count": 2
    },
    {
      "left": -0.008905275005021668,
      "right": -0.003986459509982689,
      "count": 0
    },
    {
      "left": -0.003986459509982665,
      "right": 0.0009323559850563136,
      "count": 0
    },
    {
      "left": 0.0009323559850563101,
      "right": 0.005851171480095289,
      "count": 1
    }
  ],
  "duration_minutes_histogram": [
    {
      "left": 2730.0,
      "right": 2809.3333333333335,
      "count": 1
    },
    {
      "left": 2809.3333333333335,
      "right": 2888.666666666667,
      "count": 0
    },
    {
      "left": 2888.6666666666665,
      "right": 2968.0,
      "count": 0
    },
    {
      "left": 2968.0,
      "right": 3047.3333333333335,
      "count": 0
    },
    {
      "left": 3047.3333333333335,
      "right": 3126.666666666667,
      "count": 0
    },
    {
      "left": 3126.6666666666665,
      "right": 3206.0,
      "count": 0
    },
    {
      "left": 3206.0,
      "right": 3285.3333333333335,
      "count": 0
    },
    {
      "left": 3285.333333333333,
      "right": 3364.6666666666665,
      "count": 0
    },
    {
      "left": 3364.6666666666665,
      "right": 3444.0,
      "count": 0
    },
    {
      "left": 3444.0,
      "right": 3523.3333333333335,
      "count": 0
    },
    {
      "left": 3523.333333333333,
      "right": 3602.6666666666665,
      "count": 0
    },
    {
      "left": 3602.6666666666665,
      "right": 3682.0,
      "count": 0
    },
    {
      "left": 3682.0,
      "right": 3761.3333333333335,
      "count": 0
    },
    {
      "left": 3761.333333333333,
      "right": 3840.6666666666665,
      "count": 0
    },
    {
      "left": 3840.6666666666665,
      "right": 3920.0,
      "count": 0
    },
    {
      "left": 3920.0,
      "right": 3999.3333333333335,
      "count": 0
    },
    {
      "left": 3999.333333333333,
      "right": 4078.6666666666665,
      "count": 0
    },
    {
      "left": 4078.6666666666665,
      "right": 4158.0,
      "count": 0
    },
    {
      "left": 4158.0,
      "right": 4237.333333333333,
      "count": 0
    },
    {
      "left": 4237.333333333333,
      "right": 4316.666666666666,
      "count": 0
    },
    {
      "left": 4316.666666666666,
      "right": 4395.999999999999,
      "count": 0
    },
    {
      "left": 4396.0,
      "right": 4475.333333333333,
      "count": 0
    },
    {
      "left": 4475.333333333333,
      "right": 4554.666666666666,
      "count": 0
    },
    {
      "left": 4554.666666666666,
      "right": 4633.999999999999,
      "count": 0
    },
    {
      "left": 4634.0,
      "right": 4713.333333333333,
      "count": 0
    },
    {
      "left": 4713.333333333333,
      "right": 4792.666666666666,
      "count": 0
    },
    {
      "left": 4792.666666666666,
      "right": 4871.999999999999,
      "count": 0
    },
    {
      "left": 4872.0,
      "right": 4951.333333333333,
      "count": 2
    },
    {
      "left": 4951.333333333333,
      "right": 5030.666666666666,
      "count": 0
    },
    {
      "left": 5030.666666666666,
      "right": 5109.999999999999,
      "count": 1
    }
  ],
  "weekday_winrate": {
    "2": 0.0,
    "3": 33.33333333333333
  },
  "exit_reason_counts": {
    "stop_loss": 1,
    "force_exit": 3
  }
}